lcgtools/__init__.py
lcgtools/graphics.py
lcgtools/util.py
lcgtools/apps/__init__.py
lcgtools/apps/lcgpdf.py
lcgtools/examples/mc.ini
lcgtools/scripts/__init__.py
lcgtools/scripts/cardlist.py
lcgtools/scripts/image.py
lcgtools/scripts/pdf.py
lcgtools-0.5.7.dist-info/COPYING
lcgtools-0.5.7.dist-info/COPYING.LESSER
lcgtools-0.5.7.dist-info/LICENSE
lcgtools-0.5.7.dist-info/METADATA
lcgtools-0.5.7.dist-info/WHEEL
lcgtools-0.5.7.dist-info/entry_points.txt
lcgtools-0.5.7.dist-info/top_level.txt
lcgtools-0.5.7.dist-info/RECORD
