Metadata-Version: 2.1
Name: lcgtools
Version: 0.5.7
Summary: Custom card tools for Living Card Games
Home-page: https://github.com/lcgtools/lcg_tools
Author: Cloudberries
Author-email: lcgtools@proton.me
License: GNU LGPL v3 or later
Project-URL: Bug Tracker, https://github.com/lcgtools/lcg_tools/issues
Keywords: lcgtools,lcg
Classifier: Development Status :: 3 - Alpha
Classifier: Intended Audience :: End Users/Desktop
Classifier: License :: OSI Approved :: GNU Lesser General Public License v3 or later (LGPLv3+)
Classifier: Natural Language :: English
Classifier: Operating System :: OS Independent
Classifier: Programming Language :: Python :: 3
Classifier: Topic :: Utilities
Requires-Python: <4,>=3.8
License-File: LICENSE
License-File: COPYING
License-File: COPYING.LESSER
Requires-Dist: PySide6
